[
    {
        "entry_date": "2015-08-30 22:11:17",
        "level": 300,
        "level_name": "warning",
        "message": "Invalid argument supplied for foreach()",
        "started_time": 1440990677.62,
        "previous_time": 1440990677.62,
        "current_time": 1440990677.81,
        "elapsed_time_from_start": 0.185554027557,
        "formatted_time_from_start": "0.19 seconds (+-1440990677.43)",
        "elapsed_time_from_previous": 0.185536146164,
        "formatted_time_for_step": "0.19 seconds (+-1440990677.43)",
        "memory_usage": 21.75,
        "previous_memory": 0,
        "memory_difference": 21.75,
        "formatted_memory": "21.75 MB (+21.750)",
        "file": "\/Users\/amystephen\/Sites\/Molajo\/vendor\/molajo\/query\/Source\/Query\/Model\/Criteria.php",
        "line_number": 231
    },
    {
        "entry_date": "2015-08-30 22:11:17",
        "level": 300,
        "level_name": "warning",
        "message": "Creating default object from empty value",
        "started_time": 1440990677.62,
        "previous_time": 1440990677.81,
        "current_time": 1440990677.81,
        "elapsed_time_from_start": 0.192123889923,
        "formatted_time_from_start": "0.19 seconds (+-1440990677.43)",
        "elapsed_time_from_previous": 0.00656986236572,
        "formatted_time_for_step": "0.01 seconds (+-1440990677.80)",
        "memory_usage": 22.25,
        "previous_memory": 21.75,
        "memory_difference": 0.5,
        "formatted_memory": "22.25 MB (+0.500)",
        "file": "\/Users\/amystephen\/Sites\/Molajo\/vendor\/molajo\/query\/Source\/Controller\/Read.php",
        "line_number": 232
    },
    {
        "entry_date": "2015-08-30 22:11:17",
        "level": 300,
        "level_name": "warning",
        "message": "Invalid argument supplied for foreach()",
        "started_time": 1440990677.62,
        "previous_time": 1440990677.81,
        "current_time": 1440990677.83,
        "elapsed_time_from_start": 0.210793018341,
        "formatted_time_from_start": "0.21 seconds (+-1440990677.41)",
        "elapsed_time_from_previous": 0.018669128418,
        "formatted_time_for_step": "0.02 seconds (+-1440990677.79)",
        "memory_usage": 22.5,
        "previous_memory": 22.25,
        "memory_difference": 0.25,
        "formatted_memory": "22.50 MB (+0.250)",
        "file": "\/Users\/amystephen\/Sites\/Molajo\/vendor\/molajo\/query\/Source\/Query\/Model\/Criteria.php",
        "line_number": 231
    },
    {
        "entry_date": "2015-08-30 22:11:18",
        "level": 300,
        "level_name": "warning",
        "message": "Invalid argument supplied for foreach()",
        "started_time": 1440990677.62,
        "previous_time": 1440990677.83,
        "current_time": 1440990678.08,
        "elapsed_time_from_start": 0.460232019424,
        "formatted_time_from_start": "0.46 seconds (+-1440990677.16)",
        "elapsed_time_from_previous": 0.249439001083,
        "formatted_time_for_step": "0.25 seconds (+-1440990677.58)",
        "memory_usage": 39,
        "previous_memory": 22.5,
        "memory_difference": 16.5,
        "formatted_memory": "39.00 MB (+16.500)",
        "file": "\/Users\/amystephen\/Sites\/Molajo\/vendor\/molajo\/query\/Source\/Query\/Model\/Criteria.php",
        "line_number": 231
    },
    {
        "entry_date": "2015-08-30 22:11:18",
        "level": 300,
        "level_name": "warning",
        "message": "Invalid argument supplied for foreach()",
        "started_time": 1440990677.62,
        "previous_time": 1440990678.08,
        "current_time": 1440990678.1,
        "elapsed_time_from_start": 0.477895021439,
        "formatted_time_from_start": "0.48 seconds (+-1440990677.14)",
        "elapsed_time_from_previous": 0.0176630020142,
        "formatted_time_for_step": "0.02 seconds (+-1440990678.06)",
        "memory_usage": 39,
        "previous_memory": 39,
        "memory_difference": 0,
        "formatted_memory": "39.00 MB (+0.000)",
        "file": "\/Users\/amystephen\/Sites\/Molajo\/vendor\/molajo\/query\/Source\/Query\/Model\/Criteria.php",
        "line_number": 231
    },
    {
        "entry_date": "2015-08-30 22:11:18",
        "level": 300,
        "level_name": "warning",
        "message": "Invalid argument supplied for foreach()",
        "started_time": 1440990677.62,
        "previous_time": 1440990678.1,
        "current_time": 1440990678.1,
        "elapsed_time_from_start": 0.482203006744,
        "formatted_time_from_start": "0.48 seconds (+-1440990677.14)",
        "elapsed_time_from_previous": 0.00430798530579,
        "formatted_time_for_step": "0.00 seconds (+-1440990678.09)",
        "memory_usage": 39,
        "previous_memory": 39,
        "memory_difference": 0,
        "formatted_memory": "39.00 MB (+0.000)",
        "file": "\/Users\/amystephen\/Sites\/Molajo\/vendor\/molajo\/query\/Source\/Query\/Model\/Criteria.php",
        "line_number": 231
    },
    {
        "entry_date": "2015-08-30 22:11:18",
        "level": 300,
        "level_name": "warning",
        "message": "Invalid argument supplied for foreach()",
        "started_time": 1440990677.62,
        "previous_time": 1440990678.1,
        "current_time": 1440990678.11,
        "elapsed_time_from_start": 0.486300945282,
        "formatted_time_from_start": "0.49 seconds (+-1440990677.13)",
        "elapsed_time_from_previous": 0.0040979385376,
        "formatted_time_for_step": "0.00 seconds (+-1440990678.10)",
        "memory_usage": 39,
        "previous_memory": 39,
        "memory_difference": 0,
        "formatted_memory": "39.00 MB (+0.000)",
        "file": "\/Users\/amystephen\/Sites\/Molajo\/vendor\/molajo\/query\/Source\/Query\/Model\/Criteria.php",
        "line_number": 231
    },
    {
        "entry_date": "2015-08-30 22:11:18",
        "level": 300,
        "level_name": "warning",
        "message": "Invalid argument supplied for foreach()",
        "started_time": 1440990677.62,
        "previous_time": 1440990678.11,
        "current_time": 1440990678.11,
        "elapsed_time_from_start": 0.490673065186,
        "formatted_time_from_start": "0.49 seconds (+-1440990677.13)",
        "elapsed_time_from_previous": 0.00437211990356,
        "formatted_time_for_step": "0.00 seconds (+-1440990678.10)",
        "memory_usage": 39,
        "previous_memory": 39,
        "memory_difference": 0,
        "formatted_memory": "39.00 MB (+0.000)",
        "file": "\/Users\/amystephen\/Sites\/Molajo\/vendor\/molajo\/query\/Source\/Query\/Model\/Criteria.php",
        "line_number": 231
    },
    {
        "entry_date": "2015-08-30 22:11:18",
        "level": 300,
        "level_name": "warning",
        "message": "Invalid argument supplied for foreach()",
        "started_time": 1440990677.62,
        "previous_time": 1440990678.11,
        "current_time": 1440990678.12,
        "elapsed_time_from_start": 0.494776010513,
        "formatted_time_from_start": "0.49 seconds (+-1440990677.13)",
        "elapsed_time_from_previous": 0.00410294532776,
        "formatted_time_for_step": "0.00 seconds (+-1440990678.11)",
        "memory_usage": 39,
        "previous_memory": 39,
        "memory_difference": 0,
        "formatted_memory": "39.00 MB (+0.000)",
        "file": "\/Users\/amystephen\/Sites\/Molajo\/vendor\/molajo\/query\/Source\/Query\/Model\/Criteria.php",
        "line_number": 231
    },
    {
        "entry_date": "2015-08-30 22:11:18",
        "level": 300,
        "level_name": "warning",
        "message": "Invalid argument supplied for foreach()",
        "started_time": 1440990677.62,
        "previous_time": 1440990678.12,
        "current_time": 1440990678.39,
        "elapsed_time_from_start": 0.76991891861,
        "formatted_time_from_start": "0.77 seconds (+-1440990676.85)",
        "elapsed_time_from_previous": 0.275142908096,
        "formatted_time_for_step": "0.28 seconds (+-1440990677.84)",
        "memory_usage": 39,
        "previous_memory": 39,
        "memory_difference": 0,
        "formatted_memory": "39.00 MB (+0.000)",
        "file": "\/Users\/amystephen\/Sites\/Molajo\/vendor\/molajo\/query\/Source\/Query\/Model\/Criteria.php",
        "line_number": 231
    },
    {
        "entry_date": "2015-08-30 22:11:18",
        "level": 300,
        "level_name": "warning",
        "message": "Creating default object from empty value",
        "started_time": 1440990677.62,
        "previous_time": 1440990678.39,
        "current_time": 1440990678.4,
        "elapsed_time_from_start": 0.778539896011,
        "formatted_time_from_start": "0.78 seconds (+-1440990676.84)",
        "elapsed_time_from_previous": 0.00862097740173,
        "formatted_time_for_step": "0.01 seconds (+-1440990678.38)",
        "memory_usage": 39,
        "previous_memory": 39,
        "memory_difference": 0,
        "formatted_memory": "39.00 MB (+0.000)",
        "file": "\/Users\/amystephen\/Sites\/Molajo\/Source\/Plugins\/Checkin\/Source\/CheckinPlugin.php",
        "line_number": 31
    },
    {
        "entry_date": "2015-08-30 22:11:18",
        "level": 300,
        "level_name": "warning",
        "message": "Invalid argument supplied for foreach()",
        "started_time": 1440990677.62,
        "previous_time": 1440990678.4,
        "current_time": 1440990678.43,
        "elapsed_time_from_start": 0.810950994492,
        "formatted_time_from_start": "0.81 seconds (+-1440990676.81)",
        "elapsed_time_from_previous": 0.0324110984802,
        "formatted_time_for_step": "0.03 seconds (+-1440990678.37)",
        "memory_usage": 39,
        "previous_memory": 39,
        "memory_difference": 0,
        "formatted_memory": "39.00 MB (+0.000)",
        "file": "\/Users\/amystephen\/Sites\/Molajo\/vendor\/molajo\/query\/Source\/Query\/Model\/Criteria.php",
        "line_number": 231
    },
    {
        "entry_date": "2015-08-30 22:11:18",
        "level": 300,
        "level_name": "warning",
        "message": "Invalid argument supplied for foreach()",
        "started_time": 1440990677.62,
        "previous_time": 1440990678.43,
        "current_time": 1440990678.45,
        "elapsed_time_from_start": 0.827955961227,
        "formatted_time_from_start": "0.83 seconds (+-1440990676.79)",
        "elapsed_time_from_previous": 0.0170049667358,
        "formatted_time_for_step": "0.02 seconds (+-1440990678.41)",
        "memory_usage": 39,
        "previous_memory": 39,
        "memory_difference": 0,
        "formatted_memory": "39.00 MB (+0.000)",
        "file": "\/Users\/amystephen\/Sites\/Molajo\/vendor\/molajo\/query\/Source\/Query\/Model\/Criteria.php",
        "line_number": 231
    },
    {
        "entry_date": "2015-08-30 22:11:18",
        "level": 300,
        "level_name": "warning",
        "message": "Invalid argument supplied for foreach()",
        "started_time": 1440990677.62,
        "previous_time": 1440990678.45,
        "current_time": 1440990678.45,
        "elapsed_time_from_start": 0.832823038101,
        "formatted_time_from_start": "0.83 seconds (+-1440990676.79)",
        "elapsed_time_from_previous": 0.00486707687378,
        "formatted_time_for_step": "0.00 seconds (+-1440990678.44)",
        "memory_usage": 39,
        "previous_memory": 39,
        "memory_difference": 0,
        "formatted_memory": "39.00 MB (+0.000)",
        "file": "\/Users\/amystephen\/Sites\/Molajo\/vendor\/molajo\/query\/Source\/Query\/Model\/Criteria.php",
        "line_number": 231
    },
    {
        "entry_date": "2015-08-30 22:11:18",
        "level": 300,
        "level_name": "warning",
        "message": "Invalid argument supplied for foreach()",
        "started_time": 1440990677.62,
        "previous_time": 1440990678.45,
        "current_time": 1440990678.46,
        "elapsed_time_from_start": 0.837393045425,
        "formatted_time_from_start": "0.84 seconds (+-1440990676.78)",
        "elapsed_time_from_previous": 0.00457000732422,
        "formatted_time_for_step": "0.00 seconds (+-1440990678.45)",
        "memory_usage": 39,
        "previous_memory": 39,
        "memory_difference": 0,
        "formatted_memory": "39.00 MB (+0.000)",
        "file": "\/Users\/amystephen\/Sites\/Molajo\/vendor\/molajo\/query\/Source\/Query\/Model\/Criteria.php",
        "line_number": 231
    },
    {
        "entry_date": "2015-08-30 22:11:18",
        "level": 300,
        "level_name": "warning",
        "message": "Invalid argument supplied for foreach()",
        "started_time": 1440990677.62,
        "previous_time": 1440990678.46,
        "current_time": 1440990678.46,
        "elapsed_time_from_start": 0.842012882233,
        "formatted_time_from_start": "0.84 seconds (+-1440990676.78)",
        "elapsed_time_from_previous": 0.00461983680725,
        "formatted_time_for_step": "0.00 seconds (+-1440990678.45)",
        "memory_usage": 39,
        "previous_memory": 39,
        "memory_difference": 0,
        "formatted_memory": "39.00 MB (+0.000)",
        "file": "\/Users\/amystephen\/Sites\/Molajo\/vendor\/molajo\/query\/Source\/Query\/Model\/Criteria.php",
        "line_number": 231
    },
    {
        "entry_date": "2015-08-30 22:11:18",
        "level": 300,
        "level_name": "warning",
        "message": "Invalid argument supplied for foreach()",
        "started_time": 1440990677.62,
        "previous_time": 1440990678.46,
        "current_time": 1440990678.48,
        "elapsed_time_from_start": 0.860842943192,
        "formatted_time_from_start": "0.86 seconds (+-1440990676.76)",
        "elapsed_time_from_previous": 0.0188300609589,
        "formatted_time_for_step": "0.02 seconds (+-1440990678.44)",
        "memory_usage": 39,
        "previous_memory": 39,
        "memory_difference": 0,
        "formatted_memory": "39.00 MB (+0.000)",
        "file": "\/Users\/amystephen\/Sites\/Molajo\/vendor\/molajo\/query\/Source\/Query\/Model\/Criteria.php",
        "line_number": 231
    },
    {
        "entry_date": "2015-08-30 22:11:18",
        "level": 300,
        "level_name": "warning",
        "message": "Invalid argument supplied for foreach()",
        "started_time": 1440990677.62,
        "previous_time": 1440990678.48,
        "current_time": 1440990678.49,
        "elapsed_time_from_start": 0.872146844864,
        "formatted_time_from_start": "0.87 seconds (+-1440990676.75)",
        "elapsed_time_from_previous": 0.0113039016724,
        "formatted_time_for_step": "0.01 seconds (+-1440990678.47)",
        "memory_usage": 39,
        "previous_memory": 39,
        "memory_difference": 0,
        "formatted_memory": "39.00 MB (+0.000)",
        "file": "\/Users\/amystephen\/Sites\/Molajo\/vendor\/molajo\/query\/Source\/Query\/Model\/Criteria.php",
        "line_number": 231
    },
    {
        "entry_date": "2015-08-30 22:11:18",
        "level": 300,
        "level_name": "warning",
        "message": "Creating default object from empty value",
        "started_time": 1440990677.62,
        "previous_time": 1440990678.49,
        "current_time": 1440990678.5,
        "elapsed_time_from_start": 0.875855922699,
        "formatted_time_from_start": "0.88 seconds (+-1440990676.74)",
        "elapsed_time_from_previous": 0.00370907783508,
        "formatted_time_for_step": "0.00 seconds (+-1440990678.49)",
        "memory_usage": 39,
        "previous_memory": 39,
        "memory_difference": 0,
        "formatted_memory": "39.00 MB (+0.000)",
        "file": "\/Users\/amystephen\/Sites\/Molajo\/Source\/Plugins\/Checkin\/Source\/CheckinPlugin.php",
        "line_number": 31
    },
    {
        "entry_date": "2015-08-30 22:11:18",
        "level": 300,
        "level_name": "warning",
        "message": "Invalid argument supplied for foreach()",
        "started_time": 1440990677.62,
        "previous_time": 1440990678.5,
        "current_time": 1440990678.51,
        "elapsed_time_from_start": 0.89245390892,
        "formatted_time_from_start": "0.89 seconds (+-1440990676.73)",
        "elapsed_time_from_previous": 0.0165979862213,
        "formatted_time_for_step": "0.02 seconds (+-1440990678.48)",
        "memory_usage": 39,
        "previous_memory": 39,
        "memory_difference": 0,
        "formatted_memory": "39.00 MB (+0.000)",
        "file": "\/Users\/amystephen\/Sites\/Molajo\/vendor\/molajo\/query\/Source\/Query\/Model\/Criteria.php",
        "line_number": 231
    },
    {
        "entry_date": "2015-08-30 22:11:18",
        "level": 300,
        "level_name": "warning",
        "message": "Invalid argument supplied for foreach()",
        "started_time": 1440990677.62,
        "previous_time": 1440990678.51,
        "current_time": 1440990678.53,
        "elapsed_time_from_start": 0.908781051636,
        "formatted_time_from_start": "0.91 seconds (+-1440990676.71)",
        "elapsed_time_from_previous": 0.0163271427155,
        "formatted_time_for_step": "0.02 seconds (+-1440990678.50)",
        "memory_usage": 39,
        "previous_memory": 39,
        "memory_difference": 0,
        "formatted_memory": "39.00 MB (+0.000)",
        "file": "\/Users\/amystephen\/Sites\/Molajo\/vendor\/molajo\/query\/Source\/Query\/Model\/Criteria.php",
        "line_number": 231
    },
    {
        "entry_date": "2015-08-30 22:11:18",
        "level": 300,
        "level_name": "warning",
        "message": "Invalid argument supplied for foreach()",
        "started_time": 1440990677.62,
        "previous_time": 1440990678.53,
        "current_time": 1440990678.53,
        "elapsed_time_from_start": 0.913359880447,
        "formatted_time_from_start": "0.91 seconds (+-1440990676.71)",
        "elapsed_time_from_previous": 0.00457882881165,
        "formatted_time_for_step": "0.00 seconds (+-1440990678.52)",
        "memory_usage": 39,
        "previous_memory": 39,
        "memory_difference": 0,
        "formatted_memory": "39.00 MB (+0.000)",
        "file": "\/Users\/amystephen\/Sites\/Molajo\/vendor\/molajo\/query\/Source\/Query\/Model\/Criteria.php",
        "line_number": 231
    },
    {
        "entry_date": "2015-08-30 22:11:18",
        "level": 300,
        "level_name": "warning",
        "message": "Invalid argument supplied for foreach()",
        "started_time": 1440990677.62,
        "previous_time": 1440990678.53,
        "current_time": 1440990678.55,
        "elapsed_time_from_start": 0.927484035492,
        "formatted_time_from_start": "0.93 seconds (+-1440990676.69)",
        "elapsed_time_from_previous": 0.0141241550446,
        "formatted_time_for_step": "0.01 seconds (+-1440990678.52)",
        "memory_usage": 39,
        "previous_memory": 39,
        "memory_difference": 0,
        "formatted_memory": "39.00 MB (+0.000)",
        "file": "\/Users\/amystephen\/Sites\/Molajo\/vendor\/molajo\/query\/Source\/Query\/Model\/Criteria.php",
        "line_number": 231
    },
    {
        "entry_date": "2015-08-30 22:11:18",
        "level": 300,
        "level_name": "warning",
        "message": "Invalid argument supplied for foreach()",
        "started_time": 1440990677.62,
        "previous_time": 1440990678.55,
        "current_time": 1440990678.55,
        "elapsed_time_from_start": 0.932265043259,
        "formatted_time_from_start": "0.93 seconds (+-1440990676.69)",
        "elapsed_time_from_previous": 0.00478100776672,
        "formatted_time_for_step": "0.00 seconds (+-1440990678.54)",
        "memory_usage": 39,
        "previous_memory": 39,
        "memory_difference": 0,
        "formatted_memory": "39.00 MB (+0.000)",
        "file": "\/Users\/amystephen\/Sites\/Molajo\/vendor\/molajo\/query\/Source\/Query\/Model\/Criteria.php",
        "line_number": 231
    },
    {
        "entry_date": "2015-08-30 22:11:18",
        "level": 300,
        "level_name": "warning",
        "message": "Invalid argument supplied for foreach()",
        "started_time": 1440990677.62,
        "previous_time": 1440990678.55,
        "current_time": 1440990678.56,
        "elapsed_time_from_start": 0.93673992157,
        "formatted_time_from_start": "0.94 seconds (+-1440990676.68)",
        "elapsed_time_from_previous": 0.00447487831116,
        "formatted_time_for_step": "0.00 seconds (+-1440990678.55)",
        "memory_usage": 39,
        "previous_memory": 39,
        "memory_difference": 0,
        "formatted_memory": "39.00 MB (+0.000)",
        "file": "\/Users\/amystephen\/Sites\/Molajo\/vendor\/molajo\/query\/Source\/Query\/Model\/Criteria.php",
        "line_number": 231
    },
    {
        "entry_date": "2015-08-30 22:11:18",
        "level": 300,
        "level_name": "warning",
        "message": "Frontcontroller::runStep Error for: Route",
        "started_time": 1440990677.62,
        "previous_time": 1440990678.56,
        "current_time": 1440990678.67,
        "elapsed_time_from_start": 1.05429005623,
        "formatted_time_from_start": "1.05 seconds (+-1440990676.57)",
        "elapsed_time_from_previous": 0.117550134659,
        "formatted_time_for_step": "0.12 seconds (+-1440990678.44)",
        "memory_usage": 41.25,
        "previous_memory": 39,
        "memory_difference": 2.25,
        "formatted_memory": "41.25 MB (+2.250)",
        "file": "\/Users\/amystephen\/Sites\/Molajo\/vendor\/molajo\/application\/Source\/Controller\/FrontController.php",
        "line_number": 190
    }
]