<?xml version="1.0" encoding="utf-8"?>
<install version="1.5" type="plugin" group="moovur">
	<name>Moovur - com_user</name>
	<author>Moovum</author>
	<creationDate>February 2009</creationDate>
	<copyright>Copyright (C) 2009 Moovum. All rights reserved.</copyright>
	<license>http://www.gnu.org/licenses/gpl-2.0.html GNU/GPL</license>
	<authorEmail>development@moovum.com</authorEmail>
	<authorUrl>www.moovum.com</authorUrl>
	<version>1.0.0RC1</version>
	<group>moovur</group>
	<description>Provides Moovur support for com_user tasks</description>
	<files>
		<filename plugin="moovur_com_user">moovur_com_user.php</filename>
	</files>
	<languages>
		<language tag="en-GB">en-GB.plg_moovur_moovur_com_user.ini</language>
	</languages>
	<params>
		<param name="display_login" type="radio" default="0" label="Display Login Captcha" description="Display Captcha for login forms.">
			<option value="0">No</option>
			<option value="1">Yes</option>
		</param>
		<param name="test_login" type="radio" default="0" label="Check Login Captcha" description="Check return of Captcha for login (Used for custom templates using Moovur code)">
			<option value="0">No</option>
			<option value="1">Yes</option>
		</param>
		<param name="@spacer" type="spacer" default="" label="" description="" />
		<param name="display_registration" type="radio" default="1" label="Display Registration Captcha" description="Display Captcha for registration forms.">
			<option value="0">No</option>
			<option value="1">Yes</option>
		</param>
		<param name="test_registration" type="radio" default="1" label="Check Registration Captcha" description="Check return of Captcha for registration (Used for custom templates using Moovur code)">
			<option value="0">No</option>
			<option value="1">Yes</option>
		</param>
		<param name="@spacer" type="spacer" default="" label="" description="" />
		<param name="display_remind" type="radio" default="1" label="Display Remind Username Captcha" description="Display Captcha for Username Remind forms.">
			<option value="0">No</option>
			<option value="1">Yes</option>
		</param>
		<param name="test_remind" type="radio" default="1" label="Check Remind Username Captcha" description="Check return of Captcha for remind username forms (Used for custom templates using Moovur code)">
			<option value="0">No</option>
			<option value="1">Yes</option>
		</param>
		<param name="@spacer" type="spacer" default="" label="" description="" />
		<param name="display_request_reset" type="radio" default="1" label="Display Password Reset Request Captcha" description="Display Captcha for password reset request forms.">
			<option value="0">No</option>
			<option value="1">Yes</option>
		</param>
		<param name="test_request_reset" type="radio" default="1" label="Check Password Reset Request Captcha" description="Check return of Captcha for password reset request forms (Used for custom templates using Moovur code)">
			<option value="0">No</option>
			<option value="1">Yes</option>
		</param>
		<param name="@spacer" type="spacer" default="" label="" description="" />
		<param name="display_confirm_reset" type="radio" default="1" label="Display Password Reset Confirmation Captcha" description="Display Captcha for password reset confirmation forms.">
			<option value="0">No</option>
			<option value="1">Yes</option>
		</param>
		<param name="test_confirm_reset" type="radio" default="1" label="Check Password Reset Confirmation Captcha" description="Check return of Captcha for password reset confirmation forms (Used for custom templates using Moovur code)">
			<option value="0">No</option>
			<option value="1">Yes</option>
		</param>
	</params>
</install>
