<?xml version="1.0" encoding="utf-8"?>
<model
       name="Status"
       primary_key="id"
       name_key="value">
    <table>
        <values>
            <value id="2" value="Archived"/>
            <value id="1" value="Published"/>
            <value id="0" value="Unpublished"/>
            <value id="-1" value="Trashed"/>
            <value id="-2" value="Spammed"/>
            <value id="-5" value="Draft"/>
            <value id="-10" value="Version"/>
        </values>
    </table>
</model>
